jinja_psycopg/.pytest_cache/.gitignore
jinja_psycopg/.pytest_cache/CACHEDIR.TAG
jinja_psycopg/.pytest_cache/README.md
jinja_psycopg/.pytest_cache/v/cache/nodeids
jinja_psycopg/.pytest_cache/v/cache/stepwise
jinja_psycopg/__init__.py
jinja_psycopg/context.py
jinja_psycopg/extension.py
jinja_psycopg/renderer.py
jinja_psycopg/sql.py
jinja_psycopg-0.1.0.dist-info/WHEEL
jinja_psycopg-0.1.0.dist-info/METADATA
jinja_psycopg-0.1.0.dist-info/RECORD
