Metadata-Version: 2.1
Name: jinja-psycopg
Version: 0.1.0
License: MIT
Author-email: snorkysnark <snorkysnark@gmail.com>
Requires-Python: >=3.9
Requires-Dist: jinja2>=3.1.2
Requires-Dist: psycopg>=3.0.15
